<?xml version="1.0" encoding="utf-8" ?><dwsync><file name="wl_103_web.jpg" server="ftp.greenhammerconstruction.com//public_html/testing/" local="3288362944" remote="1797374478735277196" /><file name="wl_105_web.jpg" server="ftp.greenhammerconstruction.com//public_html/testing/" local="3288364994" remote="1797374478735277196" /><file name="wl_106_web.jpg" server="ftp.greenhammerconstruction.com//public_html/testing/" local="3288365118" remote="1797374478735277196" /><file name="wl_107_web.jpg" server="ftp.greenhammerconstruction.com//public_html/testing/" local="3288365304" remote="1797374478735277256" /><file name="wl_10_web.jpg" server="ftp.greenhammerconstruction.com//public_html/testing/" local="3263305212" remote="1797374478735277256" /><file name="wl_112_web.jpg" server="ftp.greenhammerconstruction.com//public_html/testing/" local="3288365498" remote="1797374478735277256" /><file name="wl_11_web.jpg" server="ftp.greenhammerconstruction.com//public_html/testing/" local="3263305302" remote="1797374478735277256" /><file name="wl_127_web.jpg" server="ftp.greenhammerconstruction.com//public_html/testing/" local="3288365606" remote="1797374478735277316" /><file name="wl_129_web.jpg" server="ftp.greenhammerconstruction.com//public_html/testing/" local="3288365838" remote="1797374478735277316" /><file name="wl_12_web.jpg" server="ftp.greenhammerconstruction.com//public_html/testing/" local="3271817166" remote="1797374478735277316" /><file name="wl_133_web.jpg" server="ftp.greenhammerconstruction.com//public_html/testing/" local="3288365950" remote="1797374478735277316" /><file name="wl_134_web.jpg" server="ftp.greenhammerconstruction.com//public_html/testing/" local="3288366092" remote="1797374478735277316" /><file name="wl_13_web.jpg" server="ftp.greenhammerconstruction.com//public_html/testing/" local="3271817206" remote="1797374478735277376" /><file name="wl_141_web.jpg" server="ftp.greenhammerconstruction.com//public_html/testing/" local="3288366192" remote="1797374478735277376" /><file name="wl_143_web.jpg" server="ftp.greenhammerconstruction.com//public_html/testing/" local="3288373156" remote="1797374478735277376" /><file name="wl_144_web.jpg" server="ftp.greenhammerconstruction.com//public_html/testing/" local="3288373278" remote="1797374478735277376" /><file name="wl_145_web.jpg" server="ftp.greenhammerconstruction.com//public_html/testing/" local="3288373410" remote="1797374478735277376" /><file name="wl_146_web.jpg" server="ftp.greenhammerconstruction.com//public_html/testing/" local="3288373538" remote="1797374478735277376" /><file name="wl_153_web.jpg" server="ftp.greenhammerconstruction.com//public_html/testing/" local="3288373886" remote="1797374478735277376" /><file name="wl_154_web.jpg" server="ftp.greenhammerconstruction.com//public_html/testing/" local="3288374082" remote="1797374478735277376" /><file name="wl_160_web.jpg" server="ftp.greenhammerconstruction.com//public_html/testing/" local="3288374440" remote="1797374478735277376" /><file name="wl_16_web.jpg" server="ftp.greenhammerconstruction.com//public_html/testing/" local="3271817292" remote="1797374478735277376" /><file name="wl_171_web.jpg" server="ftp.greenhammerconstruction.com//public_html/testing/" local="3288374866" remote="1797374478735277376" /><file name="wl_174_web.jpg" server="ftp.greenhammerconstruction.com//public_html/testing/" local="3288375086" remote="1797374478735277376" /><file name="wl_1_web.jpg" server="ftp.greenhammerconstruction.com//public_html/testing/" local="3263304298" remote="1797374478735277376" /><file name="wl_20_web.jpg" server="ftp.greenhammerconstruction.com//public_html/testing/" local="3271817366" remote="1797374478735277376" /><file name="wl_21_web.jpg" server="ftp.greenhammerconstruction.com//public_html/testing/" local="3271817416" remote="1797374478735277436" /><file name="wl_26_web.jpg" server="ftp.greenhammerconstruction.com//public_html/testing/" local="3271817592" remote="1797374478735277436" /><file name="wl_27_web.jpg" server="ftp.greenhammerconstruction.com//public_html/testing/" local="3271817794" remote="1797374478735277436" /><file name="wl_29_web.jpg" server="ftp.greenhammerconstruction.com//public_html/testing/" local="3271817852" remote="1797374478735277436" /><file name="wl_2_web.jpg" server="ftp.greenhammerconstruction.com//public_html/testing/" local="3263304430" remote="1797374478735277436" /><file name="wl_30_web.jpg" server="ftp.greenhammerconstruction.com//public_html/testing/" local="3271817936" remote="1797374478735277436" /><file name="wl_31_web.jpg" server="ftp.greenhammerconstruction.com//public_html/testing/" local="3271818166" remote="1797374478735277436" /><file name="wl_33_web.jpg" server="ftp.greenhammerconstruction.com//public_html/testing/" local="3271818212" remote="1797374478735277436" /><file name="wl_35_web.jpg" server="ftp.greenhammerconstruction.com//public_html/testing/" local="3271818426" remote="1797374478735277436" /><file name="wl_36_web.jpg" server="ftp.greenhammerconstruction.com//public_html/testing/" local="3271818468" remote="1797374478735277436" /><file name="wl_37_web.jpg" server="ftp.greenhammerconstruction.com//public_html/testing/" local="3271818496" remote="1797374478735277436" /><file name="wl_38_web.jpg" server="ftp.greenhammerconstruction.com//public_html/testing/" local="3271818538" remote="1797374478735277436" /><file name="wl_3_web.jpg" server="ftp.greenhammerconstruction.com//public_html/testing/" local="3263304508" remote="1797374478735277496" /><file name="wl_40_web.jpg" server="ftp.greenhammerconstruction.com//public_html/testing/" local="3271818580" remote="1797374478735277496" /><file name="wl_41_web.jpg" server="ftp.greenhammerconstruction.com//public_html/testing/" local="3271818616" remote="1797374478735277496" /><file name="wl_42_web.jpg" server="ftp.greenhammerconstruction.com//public_html/testing/" local="3271818670" remote="1797374478735277496" /><file name="wl_43_web.jpg" server="ftp.greenhammerconstruction.com//public_html/testing/" local="3271818698" remote="1797374478735277496" /><file name="wl_44_web.jpg" server="ftp.greenhammerconstruction.com//public_html/testing/" local="3271818740" remote="1797374478735277496" /><file name="wl_45_web.jpg" server="ftp.greenhammerconstruction.com//public_html/testing/" local="3271818768" remote="1797374478735277496" /><file name="wl_46_web.jpg" server="ftp.greenhammerconstruction.com//public_html/testing/" local="3271818820" remote="1797374478735277496" /><file name="wl_47_web.jpg" server="ftp.greenhammerconstruction.com//public_html/testing/" local="3271818854" remote="1797374478735277496" /><file name="wl_48_web.jpg" server="ftp.greenhammerconstruction.com//public_html/testing/" local="3271818900" remote="1797374478735277496" /><file name="wl_49_web.jpg" server="ftp.greenhammerconstruction.com//public_html/testing/" local="3271818934" remote="1797374478735277496" /><file name="wl_4_web.jpg" server="ftp.greenhammerconstruction.com//public_html/testing/" local="3263304554" remote="1797374478735277496" /><file name="wl_50_web.jpg" server="ftp.greenhammerconstruction.com//public_html/testing/" local="3271818998" remote="1797374478735277496" /><file name="wl_51_web.jpg" server="ftp.greenhammerconstruction.com//public_html/testing/" local="3271819060" remote="1797374478735277556" /><file name="wl_52_web.jpg" server="ftp.greenhammerconstruction.com//public_html/testing/" local="3271819112" remote="1797374478735277556" /><file name="wl_53_web.jpg" server="ftp.greenhammerconstruction.com//public_html/testing/" local="3271819174" remote="1797374478735277556" /><file name="wl_54_web.jpg" server="ftp.greenhammerconstruction.com//public_html/testing/" local="3271819216" remote="1797374478735277556" /><file name="wl_56_web.jpg" server="ftp.greenhammerconstruction.com//public_html/testing/" local="3271819286" remote="1797374478735277556" /><file name="wl_57_web.jpg" server="ftp.greenhammerconstruction.com//public_html/testing/" local="3271820312" remote="1797374478735277556" /><file name="wl_58_web.jpg" server="ftp.greenhammerconstruction.com//public_html/testing/" local="3271820350" remote="1797374478735277616" /><file name="wl_59_web.jpg" server="ftp.greenhammerconstruction.com//public_html/testing/" local="3271820446" remote="1797374478735277616" /><file name="wl_5_web.jpg" server="ftp.greenhammerconstruction.com//public_html/testing/" local="3263304820" remote="1797374478735277676" /><file name="wl_60_web.jpg" server="ftp.greenhammerconstruction.com//public_html/testing/" local="3271820518" remote="1797374478735277676" /><file name="wl_62_web.jpg" server="ftp.greenhammerconstruction.com//public_html/testing/" local="3271820562" remote="1797374478735277676" /><file name="wl_63_web.jpg" server="ftp.greenhammerconstruction.com//public_html/testing/" local="3271820610" remote="1797374478735277676" /><file name="wl_66_web.jpg" server="ftp.greenhammerconstruction.com//public_html/testing/" local="3271820674" remote="1797374478735277676" /><file name="wl_67_web.jpg" server="ftp.greenhammerconstruction.com//public_html/testing/" local="3271820756" remote="1797374478735277676" /><file name="wl_68_web.jpg" server="ftp.greenhammerconstruction.com//public_html/testing/" local="3271820804" remote="1797374478735277676" /><file name="wl_69_web.jpg" server="ftp.greenhammerconstruction.com//public_html/testing/" local="3271820838" remote="1797374478735277676" /><file name="wl_6_web.jpg" server="ftp.greenhammerconstruction.com//public_html/testing/" local="3263304912" remote="1797374478735277676" /><file name="wl_72_web.jpg" server="ftp.greenhammerconstruction.com//public_html/testing/" local="3271820920" remote="1797374478735277736" /><file name="wl_74_web.jpg" server="ftp.greenhammerconstruction.com//public_html/testing/" local="3271820976" remote="1797374478735277736" /><file name="wl_76_web.jpg" server="ftp.greenhammerconstruction.com//public_html/testing/" local="3271821022" remote="1797374478735277736" /><file name="wl_77_web.jpg" server="ftp.greenhammerconstruction.com//public_html/testing/" local="3271821066" remote="1797374478735277736" /><file name="wl_7_web.jpg" server="ftp.greenhammerconstruction.com//public_html/testing/" local="3263304984" remote="1797374478735277736" /><file name="wl_89_web.jpg" server="ftp.greenhammerconstruction.com//public_html/testing/" local="3288362352" remote="1797374478735277736" /><file name="wl_8_web.jpg" server="ftp.greenhammerconstruction.com//public_html/testing/" local="3263305076" remote="1797374478735277736" /><file name="wl_91_web.jpg" server="ftp.greenhammerconstruction.com//public_html/testing/" local="3288362550" remote="1797374478735277736" /><file name="wl_93_web.jpg" server="ftp.greenhammerconstruction.com//public_html/testing/" local="3288361920" remote="1797374478735277736" /><file name="wl_97_web.jpg" server="ftp.greenhammerconstruction.com//public_html/testing/" local="3288362756" remote="1797374478735277736" /><file name="wl_9_web.jpg" server="ftp.greenhammerconstruction.com//public_html/testing/" local="3263305122" remote="1797374478735277736" /><file name="wl_103_web.jpg" server="ftp.greenhammerconstruction.com//public_html/" local="3344185860" remote="2270069250696952324" /><file name="wl_105_web.jpg" server="ftp.greenhammerconstruction.com//public_html/" local="3344185860" remote="2190729333450226180" /><file name="wl_106_web.jpg" server="ftp.greenhammerconstruction.com//public_html/" local="3344185860" remote="2190802811750726148" /><file name="wl_107_web.jpg" server="ftp.greenhammerconstruction.com//public_html/" local="3344185860" remote="2190808532647164420" /><file name="wl_10_web.jpg" server="ftp.greenhammerconstruction.com//public_html/" local="3344185860" remote="2190814253543602692" /><file name="wl_112_web.jpg" server="ftp.greenhammerconstruction.com//public_html/" local="3344185860" remote="2190819974440040964" /><file name="wl_11_web.jpg" server="ftp.greenhammerconstruction.com//public_html/" local="3344185920" remote="2190825695336479296" /><file name="wl_127_web.jpg" server="ftp.greenhammerconstruction.com//public_html/" local="3344185920" remote="2190831416232917568" /><file name="wl_129_web.jpg" server="ftp.greenhammerconstruction.com//public_html/" local="3344185920" remote="2190837137129355840" /><file name="wl_12_web.jpg" server="ftp.greenhammerconstruction.com//public_html/" local="3344185920" remote="2192227143165164096" /><file name="wl_133_web.jpg" server="ftp.greenhammerconstruction.com//public_html/" local="3344185920" remote="2192232864061602368" /><file name="wl_134_web.jpg" server="ftp.greenhammerconstruction.com//public_html/" local="3344185920" remote="2192238584958040640" /><file name="wl_13_web.jpg" server="ftp.greenhammerconstruction.com//public_html/" local="3344185920" remote="2192244305854478912" /><file name="wl_141_web.jpg" server="ftp.greenhammerconstruction.com//public_html/" local="3344185920" remote="2192250026750917184" /><file name="wl_143_web.jpg" server="ftp.greenhammerconstruction.com//public_html/" local="3344185920" remote="2192255747647355456" /><file name="wl_144_web.jpg" server="ftp.greenhammerconstruction.com//public_html/" local="3344185920" remote="2192261468543793728" /><file name="wl_145_web.jpg" server="ftp.greenhammerconstruction.com//public_html/" local="3344185920" remote="2195747143742143040" /><file name="wl_146_web.jpg" server="ftp.greenhammerconstruction.com//public_html/" local="3344185920" remote="2195752864638581312" /><file name="wl_153_web.jpg" server="ftp.greenhammerconstruction.com//public_html/" local="3344185920" remote="2195758585535019584" /><file name="wl_154_web.jpg" server="ftp.greenhammerconstruction.com//public_html/" local="3344185920" remote="2195764306431457856" /><file name="wl_160_web.jpg" server="ftp.greenhammerconstruction.com//public_html/" local="3344185920" remote="2195770027327896128" /><file name="wl_16_web.jpg" server="ftp.greenhammerconstruction.com//public_html/" local="3344185920" remote="2195775748224334400" /><file name="wl_171_web.jpg" server="ftp.greenhammerconstruction.com//public_html/" local="3344185920" remote="2195781469120772672" /><file name="wl_174_web.jpg" server="ftp.greenhammerconstruction.com//public_html/" local="3344185920" remote="2195887245575338560" /><file name="wl_1_web.jpg" server="ftp.greenhammerconstruction.com//public_html/" local="3344185920" remote="2195892966471776832" /><file name="wl_20_web.jpg" server="ftp.greenhammerconstruction.com//public_html/" local="3344185920" remote="2195898687368215104" /><file name="wl_21_web.jpg" server="ftp.greenhammerconstruction.com//public_html/" local="3344185920" remote="2195904408264653376" /><file name="wl_26_web.jpg" server="ftp.greenhammerconstruction.com//public_html/" local="3344185920" remote="2195910129161091648" /><file name="wl_27_web.jpg" server="ftp.greenhammerconstruction.com//public_html/" local="3344185920" remote="2195915850057529920" /><file name="wl_29_web.jpg" server="ftp.greenhammerconstruction.com//public_html/" local="3344185920" remote="2195921570953968192" /><file name="wl_2_web.jpg" server="ftp.greenhammerconstruction.com//public_html/" local="3344185980" remote="2195954779641100924" /><file name="wl_30_web.jpg" server="ftp.greenhammerconstruction.com//public_html/" local="3344185980" remote="2195960500537539196" /><file name="wl_31_web.jpg" server="ftp.greenhammerconstruction.com//public_html/" local="3344185980" remote="2195966221433977468" /><file name="wl_33_web.jpg" server="ftp.greenhammerconstruction.com//public_html/" local="3344185980" remote="2195971942330415740" /><file name="wl_35_web.jpg" server="ftp.greenhammerconstruction.com//public_html/" local="3344185980" remote="2195977663226854012" /><file name="wl_36_web.jpg" server="ftp.greenhammerconstruction.com//public_html/" local="3344185980" remote="2195983384123292284" /><file name="wl_37_web.jpg" server="ftp.greenhammerconstruction.com//public_html/" local="3344185980" remote="2195989105019730556" /><file name="wl_38_web.jpg" server="ftp.greenhammerconstruction.com//public_html/" local="3344185980" remote="2195483553009252988" /><file name="wl_3_web.jpg" server="ftp.greenhammerconstruction.com//public_html/" local="3344185980" remote="2195489273905691260" /><file name="wl_40_web.jpg" server="ftp.greenhammerconstruction.com//public_html/" local="3344185980" remote="2195494994802129532" /><file name="wl_41_web.jpg" server="ftp.greenhammerconstruction.com//public_html/" local="3344185980" remote="2195500715698567804" /><file name="wl_42_web.jpg" server="ftp.greenhammerconstruction.com//public_html/" local="3344185980" remote="2195506436595006076" /><file name="wl_43_web.jpg" server="ftp.greenhammerconstruction.com//public_html/" local="3344185980" remote="2195512157491444348" /><file name="wl_44_web.jpg" server="ftp.greenhammerconstruction.com//public_html/" local="3344185980" remote="2195517878387882620" /><file name="wl_45_web.jpg" server="ftp.greenhammerconstruction.com//public_html/" local="3344185980" remote="2195577475354081916" /><file name="wl_46_web.jpg" server="ftp.greenhammerconstruction.com//public_html/" local="3344185980" remote="2195583196250520188" /><file name="wl_47_web.jpg" server="ftp.greenhammerconstruction.com//public_html/" local="3344185980" remote="2195588917146958460" /><file name="wl_48_web.jpg" server="ftp.greenhammerconstruction.com//public_html/" local="3344185980" remote="2195594638043396732" /><file name="wl_49_web.jpg" server="ftp.greenhammerconstruction.com//public_html/" local="3344185980" remote="2195600358939835004" /><file name="wl_4_web.jpg" server="ftp.greenhammerconstruction.com//public_html/" local="3344185980" remote="2195606079836273276" /><file name="wl_50_web.jpg" server="ftp.greenhammerconstruction.com//public_html/" local="3344185980" remote="2195611800732711548" /><file name="wl_51_web.jpg" server="ftp.greenhammerconstruction.com//public_html/" local="3344185980" remote="2195617521629149820" /><file name="wl_52_web.jpg" server="ftp.greenhammerconstruction.com//public_html/" local="3344185980" remote="2195129561804716668" /><file name="wl_53_web.jpg" server="ftp.greenhammerconstruction.com//public_html/" local="3344185980" remote="2195135282701154940" /><file name="wl_54_web.jpg" server="ftp.greenhammerconstruction.com//public_html/" local="3344185980" remote="2195141003597593212" /><file name="wl_56_web.jpg" server="ftp.greenhammerconstruction.com//public_html/" local="3344185980" remote="2195146724494031484" /><file name="wl_57_web.jpg" server="ftp.greenhammerconstruction.com//public_html/" local="3344185980" remote="2195152445390469756" /><file name="wl_58_web.jpg" server="ftp.greenhammerconstruction.com//public_html/" local="3344185980" remote="2195158166286908028" /><file name="wl_59_web.jpg" server="ftp.greenhammerconstruction.com//public_html/" local="3344185980" remote="2195163887183346300" /><file name="wl_5_web.jpg" server="ftp.greenhammerconstruction.com//public_html/" local="3344185980" remote="2195232280242567804" /><file name="wl_60_web.jpg" server="ftp.greenhammerconstruction.com//public_html/" local="3344185980" remote="2195238001139006076" /><file name="wl_62_web.jpg" server="ftp.greenhammerconstruction.com//public_html/" local="3344185980" remote="2195243722035444348" /><file name="wl_63_web.jpg" server="ftp.greenhammerconstruction.com//public_html/" local="3344185980" remote="2195249442931882620" /><file name="wl_66_web.jpg" server="ftp.greenhammerconstruction.com//public_html/" local="3344185980" remote="2195255163828320892" /><file name="wl_67_web.jpg" server="ftp.greenhammerconstruction.com//public_html/" local="3344185980" remote="2195260884724759164" /><file name="wl_68_web.jpg" server="ftp.greenhammerconstruction.com//public_html/" local="3344186040" remote="2195266605621197496" /><file name="wl_69_web.jpg" server="ftp.greenhammerconstruction.com//public_html/" local="3344186040" remote="2197507633656904376" /><file name="wl_6_web.jpg" server="ftp.greenhammerconstruction.com//public_html/" local="3344186040" remote="2197513354553342648" /><file name="wl_72_web.jpg" server="ftp.greenhammerconstruction.com//public_html/" local="3344186040" remote="2197519075449780920" /><file name="wl_74_web.jpg" server="ftp.greenhammerconstruction.com//public_html/" local="3344186040" remote="2197524796346219192" /><file name="wl_76_web.jpg" server="ftp.greenhammerconstruction.com//public_html/" local="3344186040" remote="2197530517242657464" /><file name="wl_77_web.jpg" server="ftp.greenhammerconstruction.com//public_html/" local="3344186040" remote="2197536238139095736" /><file name="wl_7_web.jpg" server="ftp.greenhammerconstruction.com//public_html/" local="3344186040" remote="2197541959035534008" /><file name="wl_89_web.jpg" server="ftp.greenhammerconstruction.com//public_html/" local="3344186040" remote="2270362837481437880" /><file name="wl_8_web.jpg" server="ftp.greenhammerconstruction.com//public_html/" local="3344186040" remote="2270368558377876152" /><file name="wl_91_web.jpg" server="ftp.greenhammerconstruction.com//public_html/" local="3344186040" remote="2270374279274314424" /><file name="wl_93_web.jpg" server="ftp.greenhammerconstruction.com//public_html/" local="3344186040" remote="2270380000170752696" /><file name="wl_97_web.jpg" server="ftp.greenhammerconstruction.com//public_html/" local="3344186040" remote="2270385721067190968" /><file name="wl_9_web.jpg" server="ftp.greenhammerconstruction.com//public_html/" local="3344186040" remote="2270391441963629240" /></dwsync>